sqlalchemy_rest/__init__.py
sqlalchemy_rest/abc.py
sqlalchemy_rest/collection.py
sqlalchemy_rest/container.py
sqlalchemy_rest/framework/__init__.py
sqlalchemy_rest/framework/aiohttp.py
sqlalchemy_rest/framework/pyramid.py
sqlalchemy_rest/item.py
sqlalchemy_rest/mixin/__init__.py
sqlalchemy_rest/mixin/group_by.py
sqlalchemy_rest/mixin/paging.py
sqlalchemy_rest/mixin/params.py
sqlalchemy_rest/mixin/relation_load.py
sqlalchemy_rest/mixin/search.py
sqlalchemy_rest/typing.py
sqlalchemy_rest-0.9.0.dist-info/LICENSE.txt
sqlalchemy_rest-0.9.0.dist-info/WHEEL
sqlalchemy_rest-0.9.0.dist-info/METADATA
sqlalchemy_rest-0.9.0.dist-info/RECORD
